seriarduino/__init__.py
seriarduino-0.1.0.dist-info/METADATA
seriarduino-0.1.0.dist-info/WHEEL
seriarduino-0.1.0.dist-info/top_level.txt
seriarduino-0.1.0.dist-info/RECORD
