Metadata-Version: 2.1
Name: seriarduino
Version: 0.1.0
Summary: [BETA] Link Arduino and Python using serial port
Home-page: https://github.com/norech/SeriArduino
Author: Norech
Author-email: alexis.norech@gmail.com
License: UNKNOWN
Platform: UNKNOWN
Requires-Dist: pyserial
